matt/__init__.py
matt/argtypes.py
matt/cli.py
matt/contracts.py
matt/environment.py
matt/manager.py
matt/merkle.py
matt/script_helpers.py
matt/utils.py
matt/btctools/__init__.py
matt/btctools/_base58.py
matt/btctools/_script.py
matt/btctools/_serialize.py
matt/btctools/auth_proxy.py
matt/btctools/block.py
matt/btctools/common.py
matt/btctools/errors.py
matt/btctools/key.py
matt/btctools/messages.py
matt/btctools/psbt.py
matt/btctools/ripemd160.py
matt/btctools/script.py
matt/btctools/segwit_addr.py
matt/btctools/tx.py
matt/hub/README.md
matt/hub/__init__.py
matt/hub/fraud.py
pymatt-0.0.1.dist-info/LICENSE
pymatt-0.0.1.dist-info/METADATA
pymatt-0.0.1.dist-info/WHEEL
pymatt-0.0.1.dist-info/top_level.txt
pymatt-0.0.1.dist-info/RECORD
