Metadata-Version: 2.1
Name: pymatt
Version: 0.0.1
Summary: Merkleize All The Things
Author-email: Salvatore Ingala <salvatoshi@protonmail.com>
License: Apache License
Keywords: covenant,smart contracts,bitcoin
Requires-Python: >=3.8
License-File: LICENSE
Requires-Dist: typing-extensions >=4.9.0
